sphinx_cs/__init__.py
sphinx_cs/cs.py
sphinx_cs/debug.py
sphinx_cs/extrefs.py
sphinx_cs/extrefs_data.py
sphinx_cs-1.0.1.dist-info/LICENSE
sphinx_cs-1.0.1.dist-info/METADATA
sphinx_cs-1.0.1.dist-info/WHEEL
sphinx_cs-1.0.1.dist-info/top_level.txt
sphinx_cs-1.0.1.dist-info/RECORD
