Metadata-Version: 2.1
Name: sphinx-cs
Version: 1.0.1
Summary: C# domain for Sphinx
Home-page: https://github.com/rogerbarton/sphinx-csharp
Author: rogerbarton
Author-email: rogerbarton@users.noreply.github.com
License: MIT
Platform: UNKNOWN
Classifier: Development Status :: 4 - Beta
Classifier: Intended Audience :: Developers
Classifier: License :: OSI Approved :: MIT License
Classifier: Natural Language :: English
Classifier: Programming Language :: Python :: 3
Classifier: Operating System :: OS Independent
Classifier: Topic :: Documentation :: Sphinx
Requires-Dist: Sphinx (>=1.6)
